[{"name": "Клюква", "method": "add", "param": 8}, {"name": "Куриные голени", "method": "percent-", "param": 0.1}, {"name": "Лук-порей", "method": "add", "param": 41}, {"name": "Слива", "method": "add", "param": 92}, {"name": "Курица", "method": "percent-", "param": 0.08}, {"name": "Термосы", "method": "percent-", "param": 0.03}, {"name": "Масло подсолнечное", "method": "add", "param": 60}, {"name": "Робот-пылесос", "method": "add", "param": 86}, {"name": "Российский сыр", "method": "add", "param": 48}, {"name": "Конопляные семена", "method": "add", "param": 24}, {"name": "Наборы столовых приборов", "method": "percent-", "param": 0.08}, {"name": "Колбаса вареная", "method": "add", "param": 79}, {"name": "Пажитник сушеный", "method": "percent+", "param": 0.05}, {"name": "Пакеты для Всемирного дня поэзии", "method": "percent-", "param": 0.03}, {"name": "Темрюкская", "method": "percent+", "param": 0.02}, {"name": "Овсянка", "method": "percent-", "param": 0.07}, {"name": "Красногорская", "method": "add", "param": 50}, {"name": "Штопоры", "method": "add", "param": 10}, {"name": "Крыжовник", "method": "add", "param": 97}, {"name": "Шахтинская", "method": "sub", "param": 10}, {"name": "Мыло жидкое", "method": "percent+", "param": 0.01}, {"name": "Паприка сладкая молотая", "method": "percent-", "param": 0.01}, {"name": "Пироги с мясом", "method": "percent+", "param": 0.07}, {"name": "Редис", "method": "percent-", "param": 0.01}, {"name": "Мускатный орех молотый", "method": "sub", "param": 45}, {"name": "Подставки под горячие блюда", "method": "sub", "param": 25}, {"name": "Бадьян", "method": "percent-", "param": 0.06}, {"name": "Гранат", "method": "percent+", "param": 0.05}, {"name": "Зубная щетка", "method": "percent-", "param": 0.08}, {"name": "Сухое мясо", "method": "percent+", "param": 0.08}, {"name": "Бумажные полотенца", "method": "percent-", "param": 0.08}, {"name": "Пастернак", "method": "percent-", "param": 0.05}, {"name": "Каша из риса дикого", "method": "percent-", "param": 0.02}, {"name": "Пакеты для пляжа", "method": "percent+", "param": 0.08}, {"name": "Кострец", "method": "add", "param": 83}, {"name": "Пакеты для конференции", "method": "percent-", "param": 0.07}, {"name": "Горох", "method": "percent-", "param": 0.05}, {"name": "Рагу", "method": "percent+", "param": 0.1}, {"name": "Бекон", "method": "sub", "param": 82}, {"name": "Контейнеры для хранения продуктов", "method": "percent+", "param": 0.02}, {"name": "Смузи мангово-ананасовый", "method": "percent+", "param": 0.06}, {"name": "Экзотические виды мяса (например, страус, кенгуру)", "method": "percent-", "param": 0.02}, {"name": "Азовская", "method": "percent+", "param": 0.07}, {"name": "Пиво безалкогольное", "method": "percent+", "param": 0.03}, {"name": "Сервелат", "method": "sub", "param": 2}, {"name": "Эндивий", "method": "sub", "param": 29}, {"name": "Гауда", "method": "percent+", "param": 0.08}, {"name": "Пакеты для Дня влюбленных", "method": "percent+", "param": 0.1}, {"name": "Чечевица", "method": "add", "param": 60}, {"name": "Сибирская", "method": "sub", "param": 28}, {"name": "Вареники с мясом", "method": "percent-", "param": 0.01}, {"name": "Пакеты для Всемирного дня здоровья", "method": "percent+", "param": 0.1}, {"name": "Донер-кебаб", "method": "add", "param": 5}, {"name": "Пятновыводитель", "method": "percent-", "param": 0.02}, {"name": "Сыворотка молочная", "method": "sub", "param": 82}, {"name": "Волгодонская", "method": "percent-", "param": 0.09}, {"name": "Наволочки", "method": "percent-", "param": 0.07}, {"name": "Пакеты для документов", "method": "percent+", "param": 0.02}, {"name": "Дыня", "method": "percent+", "param": 0.07}, {"name": "Помидор", "method": "percent-", "param": 0.01}, {"name": "Верблюжье молоко", "method": "sub", "param": 22}, {"name": "Мята перечная сушеная", "method": "percent+", "param": 0.06}, {"name": "Окра", "method": "add", "param": 65}, {"name": "Сырокопченая колбаса", "method": "percent-", "param": 0.02}, {"name": "Консервы мясные", "method": "percent+", "param": 0.06}, {"name": "Ножи столовые", "method": "add", "param": 25}, {"name": "Авокадо", "method": "percent-", "param": 0.04}, {"name": "Персик", "method": "sub", "param": 70}, {"name": "Каша из булгура", "method": "percent+", "param": 0.03}, {"name": "Черника", "method": "percent-", "param": 0.09}, {"name": "Шелковица", "method": "percent+", "param": 0.09}, {"name": "Шейка", "method": "percent-", "param": 0.02}, {"name": "Пакеты для Всемирного дня окружающей среды", "method": "percent+", "param": 0.08}, {"name": "Козлятина", "method": "percent+", "param": 0.09}, {"name": "Каша из манной крупы", "method": "percent+", "param": 0.05}, {"name": "Пармезан", "method": "percent+", "param": 0.01}, {"name": "Каша из дробленного риса", "method": "percent+", "param": 0.07}, {"name": "Тэфф", "method": "percent-", "param": 0.09}, {"name": "Ветчина", "method": "add", "param": 62}, {"name": "Простокваша", "method": "sub", "param": 61}, {"name": "Аква Минерале", "method": "percent+", "param": 0.03}, {"name": "Скалки", "method": "add", "param": 28}, {"name": "Рязанская", "method": "percent+", "param": 0.09}, {"name": "Консервный нож", "method": "sub", "param": 24}, {"name": "Пакеты для мастер-класса", "method": "sub", "param": 7}, {"name": "Чай зеленый", "method": "percent-", "param": 0.1}, {"name": "Сыр", "method": "percent+", "param": 0.01}, {"name": "Прошутто", "method": "percent+", "param": 0.01}, {"name": "Шумовки", "method": "add", "param": 27}, {"name": "Пакеты для свадьбы", "method": "add", "param": 91}, {"name": "Пакеты для Дня смеха", "method": "percent-", "param": 0.04}, {"name": "Кабачок", "method": "percent+", "param": 0.01}, {"name": "Йогурт питьевой", "method": "sub", "param": 61}, {"name": "Шпик", "method": "percent+", "param": 0.07}, {"name": "Камчатская", "method": "add", "param": 21}, {"name": "Ливерная колбаса", "method": "add", "param": 57}, {"name": "Чеснок", "method": "sub", "param": 84}, {"name": "Копчености", "method": "sub", "param": 53}, {"name": "Эмменталь", "method": "sub", "param": 42}, {"name": "Нафтуся", "method": "percent+", "param": 0.04}, {"name": "Хурма", "method": "percent+", "param": 0.09}, {"name": "Мука ржаная", "method": "sub", "param": 14}, {"name": "Карамбола", "method": "add", "param": 29}, {"name": "Батат", "method": "percent+", "param": 0.01}, {"name": "Фейхоа", "method": "percent+", "param": 0.09}, {"name": "Каша из дробленой ячменя", "method": "percent+", "param": 0.01}, {"name": "Фарш куриный", "method": "sub", "param": 44}, {"name": "Подставки под столовые приборы", "method": "percent-", "param": 0.06}, {"name": "Смузи бананово-клубничный", "method": "percent-", "param": 0.1}, {"name": "Специи (перец, куркума, зира)", "method": "add", "param": 95}, {"name": "Каша из дробленной булгурной крупы", "method": "add", "param": 29}, {"name": "Патиссон", "method": "percent+", "param": 0.03}, {"name": "Салфетки влажные", "method": "add", "param": 5}, {"name": "Пакеты для охоты", "method": "percent+", "param": 0.07}, {"name": "Адыгейский сыр", "method": "percent+", "param": 0.1}, {"name": "Каша из пшеницы спельты", "method": "sub", "param": 72}, {"name": "Топлёное молоко", "method": "percent+", "param": 0.04}, {"name": "Грейпфрут", "method": "percent+", "param": 0.05}, {"name": "Моцарелла", "method": "sub", "param": 72}, {"name": "Пакеты для пикников", "method": "add", "param": 96}, {"name": "Ананас", "method": "percent-", "param": 0.06}, {"name": "Апельсин", "method": "percent-", "param": 0.01}, {"name": "Чеддер", "method": "percent-", "param": 0.07}, {"name": "Отбивная", "method": "sub", "param": 44}, {"name": "Марьинская", "method": "percent+", "param": 0.03}, {"name": "Источник Троицкий", "method": "percent-", "param": 0.04}, {"name": "Тарелки глубокие", "method": "percent-", "param": 0.02}, {"name": "Коломенская", "method": "percent-", "param": 0.06}, {"name": "Пакеты для спортивного инвентаря", "method": "percent-", "param": 0.08}, {"name": "Базилик сушеный", "method": "percent+", "param": 0.04}, {"name": "Цукини", "method": "add", "param": 87}, {"name": "Миринда", "method": "add", "param": 52}, {"name": "Джем", "method": "percent+", "param": 0.04}, {"name": "Молоко", "method": "sub", "param": 46}, {"name": "Фахитас с мясом", "method": "add", "param": 93}, {"name": "Свекла", "method": "add", "param": 39}, {"name": "Пакеты для Дня защиты детей", "method": "sub", "param": 21}, {"name": "Помело", "method": "add", "param": 61}, {"name": "Сухофрукты (изюм, курага, чернослив)", "method": "add", "param": 93}, {"name": "Курт", "method": "percent-", "param": 0.07}, {"name": "Соль", "method": "percent+", "param": 0.01}, {"name": "Матрасы", "method": "add", "param": 53}, {"name": "Ряженка", "method": "percent-", "param": 0.1}, {"name": "Сосиски", "method": "percent-", "param": 0.1}, {"name": "Ведро для мытья полов", "method": "add", "param": 39}, {"name": "Тартар", "method": "percent-", "param": 0.1}, {"name": "Калужская", "method": "percent-", "param": 0.03}, {"name": "Клубника", "method": "percent-", "param": 0.06}, {"name": "Уральская", "method": "percent-", "param": 0.04}, {"name": "Свалява", "method": "percent+", "param": 0.07}, {"name": "Портулак", "method": "percent+", "param": 0.1}, {"name": "Виноград", "method": "sub", "param": 29}, {"name": "Пастрома", "method": "sub", "param": 44}, {"name": "Pepsi Max", "method": "add", "param": 54}, {"name": "Мыло твердое", "method": "percent+", "param": 0.05}, {"name": "Имбирь молотый", "method": "percent+", "param": 0.07}, {"name": "Зефир", "method": "add", "param": 90}, {"name": "Легкое", "method": "percent-", "param": 0.09}, {"name": "Манго", "method": "add", "param": 64}, {"name": "Моющее средство для пола", "method": "add", "param": 65}, {"name": "Петрушка корневая", "method": "percent+", "param": 0.06}, {"name": "Катык", "method": "percent+", "param": 0.1}, {"name": "Кабан", "method": "percent+", "param": 0.09}, {"name": "Растительное масло кунжутное", "method": "add", "param": 58}, {"name": "Пакеты пластиковые", "method": "percent+", "param": 0.04}, {"name": "Пакеты для офиса", "method": "sub", "param": 75}, {"name": "Партенит", "method": "percent-", "param": 0.05}, {"name": "Бурятская", "method": "percent+", "param": 0.08}, {"name": "Пакеты для аукциона", "method": "add", "param": 22}, {"name": "Стиральный порошок", "method": "percent+", "param": 0.05}, {"name": "Уксус", "method": "percent-", "param": 0.02}, {"name": "Горячий шоколад", "method": "sub", "param": 100}, {"name": "Энчиладас с мясом", "method": "percent+", "param": 0.01}, {"name": "Электрочайник", "method": "add", "param": 62}, {"name": "Шубат", "method": "add", "param": 49}, {"name": "Талицкая", "method": "sub", "param": 10}, {"name": "Репа", "method": "sub", "param": 63}, {"name": "Карачинская", "method": "add", "param": 23}, {"name": "Каша из дробленной пшеничной крупы", "method": "percent+", "param": 0.01}, {"name": "Тостер", "method": "percent-", "param": 0.02}, {"name": "Пакеты для животных", "method": "percent+", "param": 0.04}, {"name": "Мороженое", "method": "percent-", "param": 0.03}, {"name": "Морковь", "method": "percent-", "param": 0.02}, {"name": "Кефир", "method": "add", "param": 83}, {"name": "Биточки", "method": "percent+", "param": 0.06}, {"name": "Консервированные бобы", "method": "sub", "param": 10}, {"name": "Лардон", "method": "add", "param": 56}, {"name": "Подушки", "method": "sub", "param": 4}, {"name": "Пакеты для школы", "method": "sub", "param": 10}, {"name": "Лимон", "method": "percent-", "param": 0.01}, {"name": "Картофель", "method": "percent-", "param": 0.1}, {"name": "Орегано сушеный", "method": "percent+", "param": 0.07}, {"name": "Ямс", "method": "percent+", "param": 0.1}, {"name": "Газированная вода", "method": "percent+", "param": 0.1}, {"name": "Златоустовская", "method": "percent+", "param": 0.06}, {"name": "Кокос", "method": "sub", "param": 14}, {"name": "Орехи (грецкий орех, миндаль, фундук)", "method": "sub", "param": 10}, {"name": "Конфи", "method": "add", "param": 89}, {"name": "Айва", "method": "percent-", "param": 0.08}, {"name": "Манты", "method": "percent+", "param": 0.03}, {"name": "Пакеты для микроволновки", "method": "sub", "param": 98}, {"name": "Бритвенный станок", "method": "add", "param": 29}, {"name": "Дезодорант", "method": "add", "param": 38}, {"name": "Сухое молоко", "method": "add", "param": 66}, {"name": "Баклажан", "method": "percent-", "param": 0.09}, {"name": "Monster Energy", "method": "add", "param": 12}, {"name": "Душистый перец горошком", "method": "add", "param": 7}, {"name": "Брокколи", "method": "sub", "param": 89}, {"name": "Каша из дробленой пшеницы", "method": "percent+", "param": 0.08}, {"name": "Нектарин", "method": "sub", "param": 73}, {"name": "Сорго", "method": "percent+", "param": 0.1}, {"name": "Лимонад классический", "method": "percent+", "param": 0.01}, {"name": "Телятина", "method": "percent+", "param": 0.1}, {"name": "Камамбер", "method": "add", "param": 28}, {"name": "Пакеты для библиотеки", "method": "percent-", "param": 0.09}, {"name": "Семечки (тыквенные, подсолнечника)", "method": "percent+", "param": 0.09}, {"name": "Сбитень медовый", "method": "percent-", "param": 0.07}, {"name": "Доски разделочные", "method": "percent+", "param": 0.07}, {"name": "Пакет для хранения продуктов", "method": "percent+", "param": 0.02}, {"name": "Малина", "method": "percent+", "param": 0.1}, {"name": "Каша из дробленой перловки", "method": "percent-", "param": 0.03}, {"name": "Шаверма", "method": "percent+", "param": 0.1}, {"name": "Обуховская", "method": "percent+", "param": 0.09}, {"name": "Пакеты для детских вещей", "method": "percent-", "param": 0.04}, {"name": "Капуста белокочанная", "method": "percent+", "param": 0.06}, {"name": "Гель для душа", "method": "percent+", "param": 0.03}, {"name": "Буковинская", "method": "sub", "param": 18}, {"name": "Груша", "method": "add", "param": 33}, {"name": "Индюшатина", "method": "percent+", "param": 0.05}, {"name": "Голова", "method": "add", "param": 44}, {"name": "Жемчужина Байкала", "method": "percent+", "param": 0.1}, {"name": "Каймак", "method": "add", "param": 32}, {"name": "Мягкие игрушки", "method": "sub", "param": 44}, {"name": "Яблоко", "method": "sub", "param": 72}, {"name": "Каша из гречки зеленой", "method": "percent+", "param": 0.08}, {"name": "Каша из дробленной овсянки", "method": "add", "param": 70}, {"name": "Пакеты для Дня космонавтики", "method": "add", "param": 15}, {"name": "Мед", "method": "percent-", "param": 0.01}, {"name": "Щавель", "method": "percent+", "param": 0.05}, {"name": "Сливки", "method": "sub", "param": 29}, {"name": "Крольчатина", "method": "sub", "param": 66}, {"name": "Пакеты для игрушек", "method": "percent+", "param": 0.03}, {"name": "Пакеты для музея", "method": "add", "param": 35}, {"name": "Варенец", "method": "percent+", "param": 0.04}, {"name": "Пакеты для Всемирного дня книг", "method": "sub", "param": 20}]